setup.py
acdata/__init__.py
acdata/acdata.py
acdata.egg-info/PKG-INFO
acdata.egg-info/SOURCES.txt
acdata.egg-info/dependency_links.txt
acdata.egg-info/top_level.txt