Metadata-Version: 2.1
Name: acdata
Version: 0.0.3
Summary: A python module to format a dataframe for plotting Andrews Curves
Author: Cole Hagen
